psopackage/__init__.py
psopackage/database/data.py
psopackage/graphics/assets/arrow-back-active.png
psopackage/graphics/assets/arrow-back.png
psopackage/graphics/assets/goodbye.png
psopackage/graphics/assets/help-active.png
psopackage/graphics/assets/help.png
psopackage/graphics/assets/info-active.png
psopackage/graphics/assets/info.png
psopackage/graphics/assets/logo.png
psopackage/graphics/assets/preview-active.png
psopackage/graphics/assets/preview.png
psopackage/graphics/assets/ubuntu-logo.png
psopackage/graphics/backButton.py
psopackage/graphics/bottomButton.py
psopackage/graphics/colors.py
psopackage/graphics/createMenu/createButton.py
psopackage/graphics/createMenu/createInput.py
psopackage/graphics/createMenu/createMenu.py
psopackage/graphics/createMenu/functionChoiceMenu.py
psopackage/graphics/exitMenu.py
psopackage/graphics/fonts.py
psopackage/graphics/gui.py
psopackage/graphics/mainMenu/__init__.py
psopackage/graphics/mainMenu/bottomButton.py
psopackage/graphics/mainMenu/bottomFrame.py
psopackage/graphics/mainMenu/mainMenu.py
psopackage/graphics/mainMenu/optionsFrame.py
psopackage/graphics/mainMenu/popUpFrame.py
psopackage/graphics/optionsButton.py
psopackage/graphics/selectMenu/optimizationFrame.py
psopackage/graphics/selectMenu/selectMenu.py
psopackage/graphics/selectMenu/viewButton.py
psopackage/graphics/selectMenu/viewFrame.py
psopackage/main.py
psopackage/optimization.py
psopackage/swarm/__init__.py
psopackage/swarm/particle.py
psopackage/swarm/particleSwarm.py
psopackage/vector/__init__.py
psopackage/vector/base_vector.py
psopackage/vector/heuristic.py
psopackage/vector/position.py
psopackage/vector/velocity.py
psopackage-1.1.0.dist-info/LICENSE
psopackage-1.1.0.dist-info/METADATA
psopackage-1.1.0.dist-info/WHEEL
psopackage-1.1.0.dist-info/entry_points.txt
psopackage-1.1.0.dist-info/RECORD
