Metadata-Version: 2.1
Name: psopackage
Version: 1.1.0
Summary: A Particle Swarm Optimization package
Home-page: https://github.com/Unbo10/ParticleSwarmOptimization
License: MIT
Author: Santiago Rocha Pachón
Author-email: srochap@unal.edu.co
Requires-Python: >=3.10
Classifier: License :: OSI Approved :: MIT License
Classifier: Programming Language :: Python :: 3
Classifier: Programming Language :: Python :: 3.10
Classifier: Programming Language :: Python :: 3.11
Classifier: Programming Language :: Python :: 3.12
Requires-Dist: matplotlib (>=3.4.3)
Requires-Dist: numpy (>=1.21.0)
Requires-Dist: openpyxl (>=3.0.9)
Requires-Dist: pandas (>=1.3.0)
Requires-Dist: setuptools (>=57.0.0)
Requires-Dist: toml (>=0.10.2)
Requires-Dist: xlsxwriter (>=1.4.3)
Project-URL: Repository, https://github.com/Unbo10/ParticleSwarmOptimization
